LICENSE
README.md
setup.cfg
setup.py
torchdynamo/__init__.py
torchdynamo/_guards.cpp
torchdynamo/allowed_functions.py
torchdynamo/bytecode_analysis.py
torchdynamo/bytecode_transformation.py
torchdynamo/codegen.py
torchdynamo/config.py
torchdynamo/convert_frame.py
torchdynamo/eval_frame.py
torchdynamo/exc.py
torchdynamo/guards.py
torchdynamo/mutation_guard.py
torchdynamo/output_graph.py
torchdynamo/profiler.py
torchdynamo/resume_execution.py
torchdynamo/side_effects.py
torchdynamo/skipfiles.py
torchdynamo/source.py
torchdynamo/symbolic_convert.py
torchdynamo/testing.py
torchdynamo/utils.py
torchdynamo/optimizations/__init__.py
torchdynamo/optimizations/analysis.py
torchdynamo/optimizations/backends.py
torchdynamo/optimizations/hash_name.py
torchdynamo/optimizations/inference.py
torchdynamo/optimizations/log_args.py
torchdynamo/optimizations/normalize.py
torchdynamo/optimizations/python_key.py
torchdynamo/optimizations/subgraph.py
torchdynamo/optimizations/training.py
torchdynamo/variables/__init__.py
torchdynamo/variables/base.py
torchdynamo/variables/builder.py
torchdynamo/variables/builtin.py
torchdynamo/variables/constant.py
torchdynamo/variables/dicts.py
torchdynamo/variables/functions.py
torchdynamo/variables/lists.py
torchdynamo/variables/misc.py
torchdynamo/variables/nn_module.py
torchdynamo/variables/tensor.py
torchdynamo/variables/torch.py
torchdynamo/variables/user_defined.py
towhee/__init__.py
towhee.compiler.egg-info/PKG-INFO
towhee.compiler.egg-info/SOURCES.txt
towhee.compiler.egg-info/dependency_links.txt
towhee.compiler.egg-info/not-zip-safe
towhee.compiler.egg-info/requires.txt
towhee.compiler.egg-info/top_level.txt
towhee/compiler/__init__.py
towhee/compiler/jit_compile.py
towhee/compiler/log.py
towhee/compiler/backends/__init__.py
towhee/compiler/backends/backend_compiler.py
towhee/compiler/backends/nebullvm_compiler.py
towhee/compiler/bytecode/__init__.py
towhee/compiler/bytecode/numba_codegen.py
towhee/compiler/frontends/__init__.py
towhee/compiler/frontends/compiler_dispatcher.py
towhee/compiler/frontends/frame_compiler.py
towhee/compiler/frontends/numba_frame_compiler.py
towhee/compiler/frontends/torch_frame_compiler.py
towhee/compiler/jit/__init__.py
