Metadata-Version: 2.1
Name: towhee.compiler
Version: 0.1.1
Summary: A JIT compiler for accelerating AI programs written in python.
Home-page: https://github.com/towhee-io/towhee-compiler
Author: Towhee Team
Author-email: towhee-team@zilliz.com
License: BSD-3
Keywords: pytorch machine learning compilers
Requires-Python: >=3.7, <3.11
License-File: LICENSE
